fhir4ds/__init__.py
fhir4ds/view_definition.py
fhir4ds/view_runner.py
fhir4ds/datastore/__init__.py
fhir4ds/datastore/batch.py
fhir4ds/datastore/connections.py
fhir4ds/datastore/core.py
fhir4ds/datastore/formatters.py
fhir4ds/datastore/result.py
fhir4ds/dialects/__init__.py
fhir4ds/dialects/base.py
fhir4ds/dialects/duckdb.py
fhir4ds/dialects/postgresql.py
fhir4ds/fhirpath/__init__.py
fhir4ds/fhirpath/fhirpath.py
fhir4ds/fhirpath/core/__init__.py
fhir4ds/fhirpath/core/builders.py
fhir4ds/fhirpath/core/choiceTypePaths.json
fhir4ds/fhirpath/core/choice_types.py
fhir4ds/fhirpath/core/constants.py
fhir4ds/fhirpath/core/generator.py
fhir4ds/fhirpath/core/translator.py
fhir4ds/fhirpath/parser/__init__.py
fhir4ds/fhirpath/parser/ast_nodes.py
fhir4ds/fhirpath/parser/parser.py
fhir4ds/helpers/__init__.py
fhir4ds/helpers/performance.py
fhir4ds/helpers/query_builder.py
fhir4ds/helpers/templates.py
fhir4ds/server/__init__.py
fhir4ds/server/__main__.py
fhir4ds/server/app.py
fhir4ds/server/config.py
fhir4ds/server/main.py
fhir4ds/server/models.py
fhir4ds/utils/__init__.py
fhir4ds/utils/performance.py
fhir4ds-0.5.1.dist-info/METADATA
fhir4ds-0.5.1.dist-info/WHEEL
fhir4ds-0.5.1.dist-info/entry_points.txt
fhir4ds-0.5.1.dist-info/licenses/LICENSE
fhir4ds-0.5.1.dist-info/RECORD
