Metadata-Version: 2.4
Name: fhir4ds
Version: 0.5.1
Summary: Production-ready healthcare analytics platform providing 100% SQL-on-FHIR v2.0 compliance with dual database support (DuckDB + PostgreSQL)
Project-URL: Documentation, https://github.com/joelmontavon/fhir4ds/blob/main/docs/README.md
Project-URL: Repository, https://github.com/joelmontavon/fhir4ds
Project-URL: Bug Tracker, https://github.com/joelmontavon/fhir4ds/issues
Project-URL: Homepage, https://github.com/joelmontavon/fhir4ds
Author-email: Joel Montavon <joelmontavon@gmail.com>
License: GNU General Public License v3 (GPLv3)
License-File: LICENSE
Keywords: analytics,data-science,duckdb,fhir,fhirpath,healthcare,postgresql,sql,viewdefinition
Classifier: Development Status :: 4 - Beta
Classifier: Intended Audience :: Developers
Classifier: Intended Audience :: Healthcare Industry
Classifier: Intended Audience :: Science/Research
Classifier: License :: OSI Approved :: GNU General Public License v3 (GPLv3)
Classifier: Programming Language :: Python :: 3
Classifier: Programming Language :: Python :: 3.8
Classifier: Programming Language :: Python :: 3.9
Classifier: Programming Language :: Python :: 3.10
Classifier: Programming Language :: Python :: 3.11
Classifier: Programming Language :: Python :: 3.12
Classifier: Topic :: Database
Classifier: Topic :: Scientific/Engineering :: Medical Science Apps.
Classifier: Topic :: Software Development :: Libraries :: Python Modules
Requires-Python: >=3.8
Requires-Dist: duckdb>=0.8.0
Requires-Dist: numpy>=1.24.4
Requires-Dist: pandas>=1.5.0
Requires-Dist: psycopg2-binary>=2.9.10
Requires-Dist: pytest>=8.3.5
Requires-Dist: typing-extensions>=4.0.0
Requires-Dist: wheel>=0.45.1
Provides-Extra: all
Requires-Dist: black>=22.0.0; extra == 'all'
Requires-Dist: fastapi>=0.100.0; extra == 'all'
Requires-Dist: flake8>=5.0.0; extra == 'all'
Requires-Dist: isort>=5.0.0; extra == 'all'
Requires-Dist: jupyter>=1.0.0; extra == 'all'
Requires-Dist: mypy>=1.0.0; extra == 'all'
Requires-Dist: notebook>=6.0.0; extra == 'all'
Requires-Dist: openpyxl>=3.0.0; extra == 'all'
Requires-Dist: psycopg2-binary>=2.9.0; extra == 'all'
Requires-Dist: pyarrow>=10.0.0; extra == 'all'
Requires-Dist: pydantic>=2.0.0; extra == 'all'
Requires-Dist: pytest-cov>=4.0.0; extra == 'all'
Requires-Dist: pytest>=7.0.0; extra == 'all'
Requires-Dist: uvicorn>=0.23.0; extra == 'all'
Provides-Extra: dev
Requires-Dist: black>=22.0.0; extra == 'dev'
Requires-Dist: flake8>=5.0.0; extra == 'dev'
Requires-Dist: isort>=5.0.0; extra == 'dev'
Requires-Dist: jupyter>=1.0.0; extra == 'dev'
Requires-Dist: mypy>=1.0.0; extra == 'dev'
Requires-Dist: notebook>=6.0.0; extra == 'dev'
Requires-Dist: pytest-cov>=4.0.0; extra == 'dev'
Requires-Dist: pytest>=7.0.0; extra == 'dev'
Provides-Extra: helpers
Requires-Dist: openpyxl>=3.0.0; extra == 'helpers'
Requires-Dist: pyarrow>=10.0.0; extra == 'helpers'
Provides-Extra: postgresql
Requires-Dist: psycopg2-binary>=2.9.0; extra == 'postgresql'
Provides-Extra: server
Requires-Dist: fastapi>=0.100.0; extra == 'server'
Requires-Dist: pydantic>=2.0.0; extra == 'server'
Requires-Dist: uvicorn>=0.23.0; extra == 'server'
